LICENSE
MANIFEST.in
README.md
requirements.txt
setup.cfg
setup.py
test-requirements.txt
async_asgi_testclient/__init__.py
async_asgi_testclient/compatibility.py
async_asgi_testclient/response.py
async_asgi_testclient/testing.py
async_asgi_testclient/utils.py
async_asgi_testclient/websocket.py
async_asgi_testclient.egg-info/PKG-INFO
async_asgi_testclient.egg-info/SOURCES.txt
async_asgi_testclient.egg-info/dependency_links.txt
async_asgi_testclient.egg-info/not-zip-safe
async_asgi_testclient.egg-info/requires.txt
async_asgi_testclient.egg-info/top_level.txt