Metadata-Version: 2.1
Name: async-asgi-testclient
Version: 1.0.0
Summary: Async client for testing ASGI web applications
Home-page: https://github.com/vinissimus/async-asgi-testclient
Author: Jordi Masip
Author-email: jordi@masip.cat
License: GNU license
Keywords: async asgi testclient
Platform: UNKNOWN
Classifier: Development Status :: 4 - Beta
Classifier: Intended Audience :: Developers
Classifier: License :: OSI Approved :: GNU General Public License v3 (GPLv3)
Classifier: Natural Language :: English
Classifier: Programming Language :: Python :: 3.6
Classifier: Programming Language :: Python :: 3.7
